pycells/__init__.py
pycells/cli.py
pycells/render.py
pycells/simulations.py
pycells/yaml.py
pycells/presets/conway.yml
pycells/presets/elementary.yml
pycells-0.1.7.dist-info/LICENSE
pycells-0.1.7.dist-info/METADATA
pycells-0.1.7.dist-info/WHEEL
pycells-0.1.7.dist-info/entry_points.txt
pycells-0.1.7.dist-info/top_level.txt
pycells-0.1.7.dist-info/RECORD
