Metadata-Version: 2.1
Name: pycells
Version: 0.1.7
Summary: A small package for simulating simple cellular automata.
Home-page: https://github.com/timfi/pycells
Author: Tim Fischer
Author-email: t.fischer98@hotmail.com
License: UNKNOWN
Platform: UNKNOWN
Classifier: Programming Language :: Python :: 3
Classifier: Operating System :: OS Independent
Requires-Python: >=3.7
Requires-Dist: Click (==7.0)
Requires-Dist: numpy (==1.18.1)
Requires-Dist: Pillow (==7.0.0)
Requires-Dist: PyYAML (==5.3)
